emoji_sentiment/Emoji_Sentiment_Data_v1.0.csv
emoji_sentiment/__init__.py
emoji_sentiment/emoji.py
emoji_sentiment-0.0.5.dist-info/licenses/LICENSE
emoji_sentiment-0.0.5.dist-info/METADATA
emoji_sentiment-0.0.5.dist-info/WHEEL
emoji_sentiment-0.0.5.dist-info/top_level.txt
emoji_sentiment-0.0.5.dist-info/RECORD
