Metadata-Version: 2.4
Name: emoji-sentiment
Version: 0.0.5
Summary: A Python package for emoji sentiment analysis.
Home-page: https://github.com/wei840222/emoji-sentiment
Author: Wan, Jiun-Wei
Author-email: wei840222@gmail.com
Requires-Python: >=3.10
License-File: LICENSE
Requires-Dist: emoji-data-python>=1.6.0
Requires-Dist: pydantic>=2.11.1
Dynamic: author
Dynamic: author-email
Dynamic: home-page
Dynamic: license-file
Dynamic: requires-python
